MANIFEST.in
README
README.md
setup.py
sphire/__init__.py
sphire.egg-info/PKG-INFO
sphire.egg-info/SOURCES.txt
sphire.egg-info/dependency_links.txt
sphire.egg-info/entry_points.txt
sphire.egg-info/top_level.txt
sphire/bin/__init__.py
sphire/bin/sp_3dvariability.py
sphire/bin/sp_ali2d.py
sphire/bin/sp_ali2d_mref.py
sphire/bin/sp_ali3d.py
sphire/bin/sp_ali_vol.py
sphire/bin/sp_auto.py
sphire/bin/sp_ave_ali.py
sphire/bin/sp_batch.py
sphire/bin/sp_center_projections.py
sphire/bin/sp_chains.py
sphire/bin/sp_cinderella_pred.py
sphire/bin/sp_compare2d.py
sphire/bin/sp_compute_isac_avg.py
sphire/bin/sp_consistency.py
sphire/bin/sp_convert_relionnew_to_relionold.py
sphire/bin/sp_copyfromtif.py
sphire/bin/sp_cpy.py
sphire/bin/sp_cryolo_boxmanager.py
sphire/bin/sp_cryolo_predict.py
sphire/bin/sp_cryolo_train.py
sphire/bin/sp_cter.py
sphire/bin/sp_ctf.py
sphire/bin/sp_ctf_refine.py
sphire/bin/sp_ctf_refine_selection.py
sphire/bin/sp_eval_isac.py
sphire/bin/sp_factcoords.py
sphire/bin/sp_filrecons3d.py
sphire/bin/sp_filterlocal.py
sphire/bin/sp_find_struct.py
sphire/bin/sp_fit_error.py
sphire/bin/sp_genbuf.py
sphire/bin/sp_gui.py
sphire/bin/sp_gui_cter.py
sphire/bin/sp_gui_meridien.py
sphire/bin/sp_gui_unblur.py
sphire/bin/sp_hac_averages.py
sphire/bin/sp_hac_clustering.py
sphire/bin/sp_header.py
sphire/bin/sp_helical_demo.py
sphire/bin/sp_helixboxer.py
sphire/bin/sp_ihrsr.py
sphire/bin/sp_imgstat.py
sphire/bin/sp_isac2.py
sphire/bin/sp_k_means.py
sphire/bin/sp_k_means_groups.py
sphire/bin/sp_k_means_stable.py
sphire/bin/sp_local_ali2d.py
sphire/bin/sp_local_ali3d.py
sphire/bin/sp_local_ali3dm.py
sphire/bin/sp_locres.py
sphire/bin/sp_mask.py
sphire/bin/sp_meridien.py
sphire/bin/sp_meridien_alpha.py
sphire/bin/sp_meridien_alpha2.py
sphire/bin/sp_meridien_beta.py
sphire/bin/sp_meridien_pre_things.py
sphire/bin/sp_meridien_sort.py
sphire/bin/sp_micrograh_selection.py
sphire/bin/sp_montage.py
sphire/bin/sp_mref_ali2d.py
sphire/bin/sp_mref_ali3d.py
sphire/bin/sp_mref_alignment.py
sphire/bin/sp_multi_ali2d.py
sphire/bin/sp_multi_assign.py
sphire/bin/sp_params_2D_to_3D.py
sphire/bin/sp_params_3D_to_2D.py
sphire/bin/sp_pca.py
