Metadata-Version: 2.1
Name: sphire
Version: 1.4.2
Summary: Python binaries and libraries for the SPHIRE cryo-EM package
Home-page: https://github.com/cryoem/eman2
Author: SPHIRE Development Team
Author-email: sphire-devel@mpi-dortmund.mpg.de
License: GPLv3
Platform: UNKNOWN
Requires-Python: >3.4.0
